swimlane_core/__init__.py
swimlane_core/__version__.py
swimlane_core/file_handler.py
swimlane_core/io_handler.py
swimlane_core-1.1.1.dist-info/METADATA
swimlane_core-1.1.1.dist-info/WHEEL
swimlane_core-1.1.1.dist-info/RECORD
