Metadata-Version: 2.1
Name: swimlane_core
Version: 1.1.1
Summary: This package provides an abstraction layer between Swimlane and Python Scripts.
Home-page: https://github.com/swimlane/swimlane_core
Keywords: connector,swimlane,connectors
Author: Swimlane
Author-email: support@swimlane.com
Maintainer: Swimlane
Requires-Python: >=3.7,<4.0
Classifier: Development Status :: 3 - Alpha
Classifier: Intended Audience :: Developers
Classifier: License :: OSI Approved :: MIT License
Classifier: Operating System :: OS Independent
Classifier: Programming Language :: Python :: 3
Classifier: Programming Language :: Python :: 3.7
Classifier: Programming Language :: Python :: 3.8
Classifier: Programming Language :: Python :: 3.9
Classifier: Programming Language :: Python :: 3.10
Classifier: Programming Language :: Python :: 3.11
Classifier: Programming Language :: Python :: 3.12
Classifier: Programming Language :: Python :: 3.6
Requires-Dist: PyYAML (>=6.0,<7.0)
Requires-Dist: requests (==2.28.0)
Project-URL: Repository, https://github.com/swimlane/swimlane_core
